radis_client/__init__.py
radis_client/client.py
radis_client/utils/__init__.py
radis_client/utils/testing_helpers.py
radis_client-0.5.4.dist-info/METADATA
radis_client-0.5.4.dist-info/WHEEL
radis_client-0.5.4.dist-info/RECORD
