Metadata-Version: 2.4
Name: radis-client
Version: 0.5.4
Summary: RADIS client library to connect to a RADIS server.
Author: Kai Schlamp
License-Expression: AGPL-3.0-or-later
Requires-Python: <4.0,>=3.12
Requires-Dist: requests>=2.32.3
